py2ren/__init__.py
py2ren/__main__.py
py2ren/cli.py
py2ren/cli.pyi
py2ren/helpers.py
py2ren/helpers.pyi
py2ren/config/__init__.py
py2ren/config/config.py
py2ren/config/config.pyi
py2ren/config/exceptions.py
py2ren/config/exceptions.pyi
py2ren/converter/__init__.py
py2ren/converter/bases.py
py2ren/converter/bases.pyi
py2ren/converter/imports.py
py2ren/converter/imports.pyi
py2ren/converter/syntax.py
py2ren/converter/syntax.pyi
py2ren/utils/__init__.py
py2ren/utils/__init__.pyi
py2ren/utils/filepath.py
py2ren/utils/filepath.pyi
py2ren/utils/iter.py
py2ren/utils/iter.pyi
py2ren-1.1.0.dist-info/licenses/LICENSE
py2ren-1.1.0.dist-info/METADATA
py2ren-1.1.0.dist-info/WHEEL
py2ren-1.1.0.dist-info/top_level.txt
py2ren-1.1.0.dist-info/RECORD
