Metadata-Version: 2.4
Name: py2ren
Version: 1.1.0
Summary: A tool to automate the transformation of native python code to renpy code.
Author-email: Yoimer Davila <yoraldarez020@gmai.com>
Maintainer-email: Yoimer Davila <yoraldarez020@gmai.com>
License: MIT License
Project-URL: Homepage, https://github.com/yoimerdr/py2ren
Project-URL: Documentation, https://yoimerdr.github.io/py2ren/docs/
Project-URL: Repository, https://github.com/yoimerdr/py2ren.git
Project-URL: Bug Tracker, https://github.com/yoimerdr/py2ren/issues
Project-URL: Changelog, https://github.com/yoimerdr/py2ren/blob/main/CHANGELOG.md
Keywords: renpy,python,transformation
Classifier: Programming Language :: Python
Classifier: Programming Language :: Python :: 2
Classifier: Programming Language :: Python :: 2.7
Classifier: Programming Language :: Python :: 3
Classifier: Programming Language :: Python :: 3.4
Classifier: Programming Language :: Python :: 3.5
Classifier: Programming Language :: Python :: 3.6
Classifier: Programming Language :: Python :: 3.7
Classifier: Programming Language :: Python :: 3.8
Requires-Python: >=2.7
License-File: LICENSE
Dynamic: license-file
